ftmplt.py
ftmplt-0.3.0.dist-info/LICENSE
ftmplt-0.3.0.dist-info/METADATA
ftmplt-0.3.0.dist-info/WHEEL
ftmplt-0.3.0.dist-info/top_level.txt
ftmplt-0.3.0.dist-info/RECORD
