Metadata-Version: 2.1
Name: ftmplt
Version: 0.3.0
Summary: Simple string parsing and formatting using Python's format strings
Author-email: Dylan Jones <dylanljones94@gmail.com>
License: MIT License
Project-URL: Source, https://github.com/dylanljones/ftmplt
Project-URL: Tracker, https://github.com/dylanljones/ftmplt/issues
Platform: any
Classifier: Development Status :: 3 - Alpha
Classifier: Intended Audience :: Developers
Classifier: License :: OSI Approved :: MIT License
Classifier: Natural Language :: English
Classifier: Programming Language :: Python :: 3
Classifier: Programming Language :: Python :: 3 :: Only
Classifier: Programming Language :: Python :: 3.7
Classifier: Programming Language :: Python :: 3.8
Classifier: Programming Language :: Python :: 3.9
Classifier: Programming Language :: Python :: 3.10
Classifier: Programming Language :: Python :: 3.11
Classifier: Programming Language :: Python :: 3.12
Requires-Python: >=3.7
License-File: LICENSE
Provides-Extra: test
Requires-Dist: pytest ; extra == 'test'
Requires-Dist: pytz ; extra == 'test'
